addition_maz/__init__.py
addition_maz/add_f.py
addition_maz/sub_f.py
addition_maz-0.0.2.dist-info/LICENSE.txt
addition_maz-0.0.2.dist-info/METADATA
addition_maz-0.0.2.dist-info/WHEEL
addition_maz-0.0.2.dist-info/top_level.txt
addition_maz-0.0.2.dist-info/RECORD
