Metadata-Version: 2.1
Name: addition-maz
Version: 0.0.2
Summary: File to add two numbers
Home-page: UNKNOWN
Author: SYED MAZHAR
Author-email: eusyedmazhar2806@gmail.com
License: MIT
Keywords: add
Platform: UNKNOWN
Classifier: Development Status :: 3 - Alpha
Classifier: Intended Audience :: Developers
Classifier: Topic :: Software Development :: Build Tools
Classifier: License :: OSI Approved :: MIT License
Classifier: Programming Language :: Python :: 3
Classifier: Programming Language :: Python :: 3.4
Classifier: Programming Language :: Python :: 3.5
Classifier: Programming Language :: Python :: 3.6
